newron/__init__.py
newron/artifacts.py
newron/auth.py
newron/catboost.py
newron/diviner.py
newron/entities.py
newron/exceptions.py
newron/fastai.py
newron/gluon.py
newron/keras.py
newron/lightgbm.py
newron/models.py
newron/prophet.py
newron/pytorch.py
newron/sklearn.py
newron/spacy.py
newron/spark.py
newron/tensorflow.py
newron/tracking.py
newron/version.py
newron_sdk-0.1.4.dist-info/LICENSE
newron_sdk-0.1.4.dist-info/METADATA
newron_sdk-0.1.4.dist-info/WHEEL
newron_sdk-0.1.4.dist-info/entry_points.txt
newron_sdk-0.1.4.dist-info/top_level.txt
newron_sdk-0.1.4.dist-info/RECORD
